ri_common-0.0.4.dist-info/licenses/LICENSE
riu/__init__.py
riu/entity.py
riu/hierarchy.py
riu/journal.py
riu/plugin.py
riu/time.py
riu/utility.py
riu/resources/README.md
riu/resources/requirements-testing.txt
riu/resources/requirements.txt
ri_common-0.0.4.dist-info/METADATA
ri_common-0.0.4.dist-info/WHEEL
ri_common-0.0.4.dist-info/top_level.txt
ri_common-0.0.4.dist-info/RECORD
