Metadata-Version: 2.4
Name: ri-common
Version: 0.0.4
Summary: Common, reusable utilities
Author: Dustin Oprea
Author-email: dustin@randomingenuity.com
License-File: LICENSE
Requires-Dist: build
Requires-Dist: twine
Requires-Dist: python-dateutil
Dynamic: author
Dynamic: author-email
Dynamic: description
Dynamic: description-content-type
Dynamic: license-file
Dynamic: requires-dist
Dynamic: summary
